[
{
"Question":"What is 25% of 480? / 480 का 25% कितना है?",
"A":"100 / 100",
"B":"110 / 110",
"C":"120 / 120",
"D":"125 / 125",
"Correct":"C"
},
{
"Question":"The HCF of 24 and 36 is: / 24 और 36 का महत्तम समापवर्तक (HCF) क्या है?",
"A":"6 / 6",
"B":"8 / 8",
"C":"10 / 10",
"D":"12 / 12",
"Correct":"D"
},
{
"Question":"The LCM of 12 and 15 is: / 12 और 15 का लघुत्तम समापवर्त्य (LCM) क्या है?",
"A":"30 / 30",
"B":"45 / 45",
"C":"60 / 60",
"D":"90 / 90",
"Correct":"C"
},
{
"Question":"What is 3/5 of 250? / 250 का 3/5 कितना है?",
"A":"120 / 120",
"B":"130 / 130",
"C":"140 / 140",
"D":"150 / 150",
"Correct":"D"
},
{
"Question":"A shopkeeper buys an article for ₹400 and sells it for ₹460. What is the profit percentage? / एक दुकानदार ₹400 में वस्तु खरीदकर ₹460 में बेचता है। लाभ प्रतिशत कितना है?",
"A":"10% / 10%",
"B":"12% / 12%",
"C":"15% / 15%",
"D":"18% / 18%",
"Correct":"C"
},
{
"Question":"The average of 12, 18, 24, 30 and 36 is: / 12, 18, 24, 30 तथा 36 का औसत क्या है?",
"A":"22 / 22",
"B":"24 / 24",
"C":"26 / 26",
"D":"28 / 28",
"Correct":"B"
},
{
"Question":"What is 18 × 12? / 18 × 12 कितना होगा?",
"A":"196 / 196",
"B":"206 / 206",
"C":"216 / 216",
"D":"226 / 226",
"Correct":"C"
},
{
"Question":"A number is divided by 8 leaving remainder 3. What will be the remainder when the same number is divided by 4? / किसी संख्या को 8 से भाग देने पर शेष 3 बचता है। उसी संख्या को 4 से भाग देने पर शेष क्या होगा?",
"A":"0 / 0",
"B":"1 / 1",
"C":"2 / 2",
"D":"3 / 3",
"Correct":"D"
},
{
"Question":"What is 15% of 800? / 800 का 15% कितना है?",
"A":"100 / 100",
"B":"110 / 110",
"C":"120 / 120",
"D":"140 / 140",
"Correct":"C"
},
{
"Question":"The sum of two numbers is 60 and their difference is 20. The larger number is: / दो संख्याओं का योग 60 तथा अंतर 20 है। बड़ी संख्या क्या है?",
"A":"30 / 30",
"B":"35 / 35",
"C":"40 / 40",
"D":"45 / 45",
"Correct":"C"
},
{
"Question":"A train travels 180 km in 3 hours. Its speed is: / एक ट्रेन 3 घंटे में 180 किमी चलती है। उसकी गति क्या है?",
"A":"50 km/h",
"B":"55 km/h",
"C":"60 km/h",
"D":"65 km/h",
"Correct":"C"
},
{
"Question":"What is the square of 19? / 19 का वर्ग कितना है?",
"A":"341 / 341",
"B":"351 / 351",
"C":"361 / 361",
"D":"381 / 381",
"Correct":"C"
},
{
"Question":"If x = 8, then the value of 2x + 5 is: / यदि x = 8 है, तो 2x + 5 का मान क्या होगा?",
"A":"19 / 19",
"B":"20 / 20",
"C":"21 / 21",
"D":"22 / 22",
"Correct":"C"
},
{
"Question":"The perimeter of a square of side 9 cm is: / 9 सेमी भुजा वाले वर्ग का परिमाप कितना होगा?",
"A":"27 cm",
"B":"36 cm",
"C":"45 cm",
"D":"81 cm",
"Correct":"B"
},
{
"Question":"Convert 0.75 into percentage. / 0.75 को प्रतिशत में बदलें।",
"A":"25% / 25%",
"B":"50% / 50%",
"C":"75% / 75%",
"D":"80% / 80%",
"Correct":"C"
},
{
"Question":"A man completes a work in 12 days. His one day's work is: / एक व्यक्ति किसी कार्य को 12 दिनों में पूरा करता है। एक दिन का कार्य कितना होगा?",
"A":"1/10",
"B":"1/11",
"C":"1/12",
"D":"1/13",
"Correct":"C"
},
{
"Question":"The simple interest on ₹2000 at 10% per annum for 2 years is: / ₹2000 पर 10% वार्षिक दर से 2 वर्ष का साधारण ब्याज कितना होगा?",
"A":"₹200",
"B":"₹300",
"C":"₹400",
"D":"₹500",
"Correct":"C"
},
{
"Question":"The ratio of 24 : 36 in simplest form is: / 24 : 36 का सरलतम रूप क्या है?",
"A":"2 : 3",
"B":"3 : 4",
"C":"4 : 5",
"D":"5 : 6",
"Correct":"A"
},
{
"Question":"What is 7² + 3²? / 7² + 3² कितना होगा?",
"A":"49",
"B":"52",
"C":"58",
"D":"60",
"Correct":"C"
},
{
"Question":"The area of a rectangle of length 12 cm and breadth 8 cm is: / 12 सेमी लंबाई तथा 8 सेमी चौड़ाई वाले आयत का क्षेत्रफल कितना होगा?",
"A":"80 cm²",
"B":"88 cm²",
"C":"96 cm²",
"D":"104 cm²",
"Correct":"C"
},
{
"Question":"What is 35% of 400? / 400 का 35% कितना है?",
"A":"120 / 120",
"B":"130 / 130",
"C":"140 / 140",
"D":"150 / 150",
"Correct":"C"
},
{
"Question":"The value of 48 ÷ 6 × 5 is: / 48 ÷ 6 × 5 का मान क्या है?",
"A":"35 / 35",
"B":"40 / 40",
"C":"45 / 45",
"D":"50 / 50",
"Correct":"B"
},
{
"Question":"The square root of 625 is: / 625 का वर्गमूल क्या है?",
"A":"15 / 15",
"B":"20 / 20",
"C":"25 / 25",
"D":"30 / 30",
"Correct":"C"
},
{
"Question":"A shirt marked at ₹800 is sold at a 10% discount. What is the selling price? / ₹800 अंकित मूल्य वाली शर्ट पर 10% की छूट दी जाती है। विक्रय मूल्य कितना होगा?",
"A":"₹700",
"B":"₹710",
"C":"₹720",
"D":"₹740",
"Correct":"C"
},
{
"Question":"The average of 15, 20, 25, 30 and 35 is: / 15, 20, 25, 30 तथा 35 का औसत क्या है?",
"A":"23",
"B":"24",
"C":"25",
"D":"26",
"Correct":"C"
},
{
"Question":"What is 9 × 17? / 9 × 17 कितना होगा?",
"A":"143",
"B":"153",
"C":"163",
"D":"173",
"Correct":"B"
},
{
"Question":"A car covers 240 km in 4 hours. Its speed is: / एक कार 4 घंटे में 240 किमी चलती है। उसकी गति क्या है?",
"A":"50 km/h",
"B":"55 km/h",
"C":"60 km/h",
"D":"65 km/h",
"Correct":"C"
},
{
"Question":"The cube of 6 is: / 6 का घन क्या है?",
"A":"196",
"B":"206",
"C":"216",
"D":"226",
"Correct":"C"
},
{
"Question":"If x = 12, then x² − 20 = ? / यदि x = 12 है, तो x² − 20 का मान क्या होगा?",
"A":"114",
"B":"120",
"C":"124",
"D":"128",
"Correct":"C"
},
{
"Question":"The perimeter of a rectangle of length 15 cm and breadth 10 cm is: / 15 सेमी लंबाई तथा 10 सेमी चौड़ाई वाले आयत का परिमाप कितना होगा?",
"A":"40 cm",
"B":"45 cm",
"C":"50 cm",
"D":"55 cm",
"Correct":"C"
},
{
"Question":"Convert 3/8 into percentage. / 3/8 को प्रतिशत में बदलें।",
"A":"35.5%",
"B":"37.5%",
"C":"40%",
"D":"42.5%",
"Correct":"B"
},
{
"Question":"A work is completed in 20 days. One day's work is: / कोई कार्य 20 दिनों में पूरा होता है। एक दिन का कार्य कितना होगा?",
"A":"1/10",
"B":"1/15",
"C":"1/20",
"D":"1/25",
"Correct":"C"
},
{
"Question":"The simple interest on ₹5000 at 8% per annum for 2 years is: / ₹5000 पर 8% वार्षिक दर से 2 वर्ष का साधारण ब्याज कितना होगा?",
"A":"₹600",
"B":"₹700",
"C":"₹800",
"D":"₹900",
"Correct":"C"
},
{
"Question":"The ratio 45 : 60 in simplest form is: / 45 : 60 का सरलतम रूप क्या है?",
"A":"2 : 3",
"B":"3 : 4",
"C":"4 : 5",
"D":"5 : 6",
"Correct":"B"
},
{
"Question":"What is 11²? / 11² कितना होता है?",
"A":"111",
"B":"121",
"C":"131",
"D":"141",
"Correct":"B"
},
{
"Question":"The area of a square of side 14 cm is: / 14 सेमी भुजा वाले वर्ग का क्षेत्रफल कितना होगा?",
"A":"176 cm²",
"B":"186 cm²",
"C":"196 cm²",
"D":"206 cm²",
"Correct":"C"
},
{
"Question":"A number increased by 25 is 80. The number is: / किसी संख्या में 25 जोड़ने पर 80 प्राप्त होता है। संख्या क्या है?",
"A":"45",
"B":"50",
"C":"55",
"D":"60",
"Correct":"C"
},
{
"Question":"A shopkeeper buys an article for ₹600 and sells it for ₹540. What is the loss percentage? / एक दुकानदार ₹600 में वस्तु खरीदकर ₹540 में बेचता है। हानि प्रतिशत कितना है?",
"A":"5%",
"B":"8%",
"C":"10%",
"D":"12%",
"Correct":"C"
},
{
"Question":"What is 2/3 of 360? / 360 का 2/3 कितना है?",
"A":"220",
"B":"230",
"C":"240",
"D":"250",
"Correct":"C"
},
{
"Question":"The circumference of a circle of radius 7 cm is (Take π = 22/7): / 7 सेमी त्रिज्या वाले वृत्त की परिधि क्या होगी? (π = 22/7 लें)",
"A":"22 cm",
"B":"44 cm",
"C":"66 cm",
"D":"88 cm",
"Correct":"B"
},
{
"Question":"What is 45% of 600? / 600 का 45% कितना है?",
"A":"250 / 250",
"B":"260 / 260",
"C":"270 / 270",
"D":"280 / 280",
"Correct":"C"
},
{
"Question":"The HCF of 18, 24 and 30 is: / 18, 24 तथा 30 का HCF क्या है?",
"A":"4 / 4",
"B":"5 / 5",
"C":"6 / 6",
"D":"8 / 8",
"Correct":"C"
},
{
"Question":"The LCM of 8, 12 and 20 is: / 8, 12 तथा 20 का LCM क्या है?",
"A":"80 / 80",
"B":"100 / 100",
"C":"120 / 120",
"D":"160 / 160",
"Correct":"C"
},
{
"Question":"A train travels 360 km in 6 hours. Its speed is: / एक ट्रेन 6 घंटे में 360 किमी चलती है। उसकी गति क्या है?",
"A":"50 km/h",
"B":"55 km/h",
"C":"60 km/h",
"D":"65 km/h",
"Correct":"C"
},
{
"Question":"The average of 18, 22, 26, 30 and 34 is: / 18, 22, 26, 30 तथा 34 का औसत क्या है?",
"A":"24",
"B":"25",
"C":"26",
"D":"27",
"Correct":"C"
},
{
"Question":"What is the square of 24? / 24 का वर्ग कितना है?",
"A":"556",
"B":"576",
"C":"596",
"D":"616",
"Correct":"B"
},
{
"Question":"A man buys an article for ₹750 and sells it for ₹900. What is the profit percentage? / एक व्यक्ति ₹750 में वस्तु खरीदकर ₹900 में बेचता है। लाभ प्रतिशत कितना है?",
"A":"15%",
"B":"18%",
"C":"20%",
"D":"25%",
"Correct":"C"
},
{
"Question":"What is 7/8 of 320? / 320 का 7/8 कितना है?",
"A":"260",
"B":"270",
"C":"280",
"D":"290",
"Correct":"C"
},
{
"Question":"The value of 15 × 8 − 20 is: / 15 × 8 − 20 का मान क्या है?",
"A":"90",
"B":"95",
"C":"100",
"D":"105",
"Correct":"C"
},
{
"Question":"If x = 15, then 3x − 10 = ? / यदि x = 15 है, तो 3x − 10 का मान क्या होगा?",
"A":"30",
"B":"35",
"C":"40",
"D":"45",
"Correct":"B"
},
{
"Question":"The area of a rectangle of length 18 cm and breadth 12 cm is: / 18 सेमी लंबाई तथा 12 सेमी चौड़ाई वाले आयत का क्षेत्रफल कितना होगा?",
"A":"196 cm²",
"B":"206 cm²",
"C":"216 cm²",
"D":"226 cm²",
"Correct":"C"
},
{
"Question":"Convert 0.625 into percentage. / 0.625 को प्रतिशत में बदलें।",
"A":"60%",
"B":"62.5%",
"C":"65%",
"D":"67.5%",
"Correct":"B"
},
{
"Question":"The simple interest on ₹3000 at 12% per annum for 2 years is: / ₹3000 पर 12% वार्षिक दर से 2 वर्ष का साधारण ब्याज कितना होगा?",
"A":"₹600",
"B":"₹660",
"C":"₹720",
"D":"₹840",
"Correct":"C"
},
{
"Question":"The ratio 56 : 72 in simplest form is: / 56 : 72 का सरलतम रूप क्या है?",
"A":"6 : 7",
"B":"7 : 8",
"C":"8 : 9",
"D":"9 : 10",
"Correct":"B"
},
{
"Question":"A work is completed in 15 days. One day's work is: / कोई कार्य 15 दिनों में पूरा होता है। एक दिन का कार्य कितना होगा?",
"A":"1/12",
"B":"1/13",
"C":"1/14",
"D":"1/15",
"Correct":"D"
},
{
"Question":"The cube of 8 is: / 8 का घन क्या है?",
"A":"256",
"B":"384",
"C":"512",
"D":"640",
"Correct":"C"
},
{
"Question":"A number is decreased by 18 to get 42. The number is: / किसी संख्या में से 18 घटाने पर 42 प्राप्त होता है। संख्या क्या है?",
"A":"50",
"B":"55",
"C":"60",
"D":"65",
"Correct":"C"
},
{
"Question":"A shopkeeper gives a 20% discount on an article marked ₹1500. What is the selling price? / ₹1500 अंकित मूल्य वाली वस्तु पर 20% की छूट दी जाती है। विक्रय मूल्य कितना होगा?",
"A":"₹1100",
"B":"₹1150",
"C":"₹1200",
"D":"₹1250",
"Correct":"C"
},
{
"Question":"What is 75% of 240? / 240 का 75% कितना है?",
"A":"160",
"B":"170",
"C":"180",
"D":"190",
"Correct":"C"
},
{
"Question":"The perimeter of a square of side 16 cm is: / 16 सेमी भुजा वाले वर्ग का परिमाप कितना होगा?",
"A":"48 cm",
"B":"56 cm",
"C":"64 cm",
"D":"72 cm",
"Correct":"C"
},
{
"Question":"What is 12.5% of 640? / 640 का 12.5% कितना है?",
"A":"60 / 60",
"B":"70 / 70",
"C":"80 / 80",
"D":"90 / 90",
"Correct":"C"
},
{
"Question":"The HCF of 42 and 56 is: / 42 और 56 का HCF क्या है?",
"A":"7 / 7",
"B":"14 / 14",
"C":"21 / 21",
"D":"28 / 28",
"Correct":"B"
},
{
"Question":"The LCM of 18 and 24 is: / 18 और 24 का LCM क्या है?",
"A":"48 / 48",
"B":"60 / 60",
"C":"72 / 72",
"D":"96 / 96",
"Correct":"C"
},
{
"Question":"A train covers 420 km in 7 hours. Its speed is: / एक ट्रेन 7 घंटे में 420 किमी तय करती है। उसकी गति क्या है?",
"A":"50 km/h",
"B":"55 km/h",
"C":"60 km/h",
"D":"65 km/h",
"Correct":"C"
},
{
"Question":"The average of 21, 24, 27, 30 and 33 is: / 21, 24, 27, 30 तथा 33 का औसत क्या है?",
"A":"25",
"B":"26",
"C":"27",
"D":"28",
"Correct":"C"
},
{
"Question":"What is the square of 26? / 26 का वर्ग कितना है?",
"A":"656",
"B":"676",
"C":"696",
"D":"706",
"Correct":"B"
},
{
"Question":"A shopkeeper buys an article for ₹500 and sells it for ₹575. What is the profit percentage? / एक दुकानदार ₹500 में वस्तु खरीदकर ₹575 में बेचता है। लाभ प्रतिशत कितना है?",
"A":"10%",
"B":"12%",
"C":"15%",
"D":"18%",
"Correct":"C"
},
{
"Question":"What is 5/6 of 360? / 360 का 5/6 कितना है?",
"A":"280",
"B":"290",
"C":"300",
"D":"320",
"Correct":"C"
},
{
"Question":"Evaluate: 18 × 9 − 42 = ? / 18 × 9 − 42 का मान क्या होगा?",
"A":"110",
"B":"120",
"C":"130",
"D":"140",
"Correct":"B"
},
{
"Question":"If x = 14, then 4x + 8 = ? / यदि x = 14 है, तो 4x + 8 का मान क्या होगा?",
"A":"60",
"B":"62",
"C":"64",
"D":"66",
"Correct":"C"
},
{
"Question":"The area of a rectangle of length 20 cm and breadth 15 cm is: / 20 सेमी लंबाई तथा 15 सेमी चौड़ाई वाले आयत का क्षेत्रफल कितना होगा?",
"A":"250 cm²",
"B":"280 cm²",
"C":"300 cm²",
"D":"320 cm²",
"Correct":"C"
},
{
"Question":"Convert 0.875 into percentage. / 0.875 को प्रतिशत में बदलें।",
"A":"75%",
"B":"80%",
"C":"85%",
"D":"87.5%",
"Correct":"D"
},
{
"Question":"The simple interest on ₹4000 at 10% per annum for 3 years is: / ₹4000 पर 10% वार्षिक दर से 3 वर्ष का साधारण ब्याज कितना होगा?",
"A":"₹1000",
"B":"₹1100",
"C":"₹1200",
"D":"₹1300",
"Correct":"C"
},
{
"Question":"The ratio 63 : 84 in simplest form is: / 63 : 84 का सरलतम रूप क्या है?",
"A":"2 : 3",
"B":"3 : 4",
"C":"4 : 5",
"D":"5 : 6",
"Correct":"B"
},
{
"Question":"A person completes a work in 25 days. One day's work is: / एक व्यक्ति किसी कार्य को 25 दिनों में पूरा करता है। एक दिन का कार्य कितना होगा?",
"A":"1/20",
"B":"1/22",
"C":"1/25",
"D":"1/30",
"Correct":"C"
},
{
"Question":"The cube of 9 is: / 9 का घन क्या है?",
"A":"648",
"B":"729",
"C":"756",
"D":"810",
"Correct":"B"
},
{
"Question":"A number increased by 32 becomes 85. Find the number. / किसी संख्या में 32 जोड़ने पर 85 प्राप्त होता है। संख्या ज्ञात करें।",
"A":"51",
"B":"52",
"C":"53",
"D":"54",
"Correct":"C"
},
{
"Question":"A shopkeeper allows a 15% discount on an article marked ₹2000. What is the selling price? / ₹2000 अंकित मूल्य वाली वस्तु पर 15% की छूट दी जाती है। विक्रय मूल्य कितना होगा?",
"A":"₹1600",
"B":"₹1650",
"C":"₹1700",
"D":"₹1800",
"Correct":"C"
},
{
"Question":"What is 40% of 450? / 450 का 40% कितना है?",
"A":"160",
"B":"170",
"C":"180",
"D":"190",
"Correct":"C"
},
{
"Question":"The circumference of a circle of radius 14 cm is (Take π = 22/7). / 14 सेमी त्रिज्या वाले वृत्त की परिधि ज्ञात करें (π = 22/7 लें)।",
"A":"66 cm",
"B":"77 cm",
"C":"88 cm",
"D":"92 cm",
"Correct":"C"
},
{
"Question":"What is 20% of 750? / 750 का 20% कितना है?",
"A":"120 / 120",
"B":"130 / 130",
"C":"140 / 140",
"D":"150 / 150",
"Correct":"D"
},
{
"Question":"The HCF of 45 and 75 is: / 45 और 75 का HCF क्या है?",
"A":"5 / 5",
"B":"10 / 10",
"C":"15 / 15",
"D":"25 / 25",
"Correct":"C"
},
{
"Question":"The LCM of 16 and 20 is: / 16 और 20 का LCM क्या है?",
"A":"60 / 60",
"B":"70 / 70",
"C":"80 / 80",
"D":"90 / 90",
"Correct":"C"
},
{
"Question":"A bus travels 300 km in 5 hours. Its speed is: / एक बस 5 घंटे में 300 किमी चलती है। उसकी गति क्या है?",
"A":"50 km/h",
"B":"55 km/h",
"C":"60 km/h",
"D":"65 km/h",
"Correct":"C"
},
{
"Question":"The average of 14, 18, 22, 26 and 30 is: / 14, 18, 22, 26 तथा 30 का औसत क्या है?",
"A":"20",
"B":"21",
"C":"22",
"D":"23",
"Correct":"C"
},
{
"Question":"What is the square of 28? / 28 का वर्ग कितना है?",
"A":"676",
"B":"729",
"C":"784",
"D":"812",
"Correct":"C"
},
{
"Question":"A trader buys an article for ₹800 and sells it for ₹920. What is the profit percentage? / एक व्यापारी ₹800 में वस्तु खरीदकर ₹920 में बेचता है। लाभ प्रतिशत कितना है?",
"A":"10%",
"B":"12%",
"C":"15%",
"D":"18%",
"Correct":"C"
},
{
"Question":"What is 9/10 of 500? / 500 का 9/10 कितना है?",
"A":"430",
"B":"440",
"C":"450",
"D":"460",
"Correct":"C"
},
{
"Question":"Evaluate: 25 × 8 − 40 = ? / 25 × 8 − 40 का मान ज्ञात करें।",
"A":"140",
"B":"150",
"C":"160",
"D":"170",
"Correct":"C"
},
{
"Question":"If x = 18, then 5x − 15 = ? / यदि x = 18 है, तो 5x − 15 का मान क्या होगा?",
"A":"70",
"B":"75",
"C":"80",
"D":"85",
"Correct":"B"
},
{
"Question":"The area of a rectangle of length 25 cm and breadth 16 cm is: / 25 सेमी लंबाई तथा 16 सेमी चौड़ाई वाले आयत का क्षेत्रफल कितना होगा?",
"A":"350 cm²",
"B":"375 cm²",
"C":"400 cm²",
"D":"425 cm²",
"Correct":"C"
},
{
"Question":"Convert 0.45 into percentage. / 0.45 को प्रतिशत में बदलें।",
"A":"40%",
"B":"45%",
"C":"50%",
"D":"55%",
"Correct":"B"
},
{
"Question":"The simple interest on ₹6000 at 5% per annum for 4 years is: / ₹6000 पर 5% वार्षिक दर से 4 वर्ष का साधारण ब्याज कितना होगा?",
"A":"₹1000",
"B":"₹1100",
"C":"₹1200",
"D":"₹1300",
"Correct":"C"
},
{
"Question":"The ratio 72 : 96 in simplest form is: / 72 : 96 का सरलतम रूप क्या है?",
"A":"2 : 3",
"B":"3 : 4",
"C":"4 : 5",
"D":"5 : 6",
"Correct":"B"
},
{
"Question":"A person completes a work in 40 days. One day's work is: / एक व्यक्ति किसी कार्य को 40 दिनों में पूरा करता है। एक दिन का कार्य कितना होगा?",
"A":"1/20",
"B":"1/30",
"C":"1/40",
"D":"1/50",
"Correct":"C"
},
{
"Question":"The cube of 12 is: / 12 का घन कितना है?",
"A":"1440",
"B":"1560",
"C":"1728",
"D":"1824",
"Correct":"C"
},
{
"Question":"A number decreased by 28 becomes 64. Find the number. / किसी संख्या में से 28 घटाने पर 64 प्राप्त होता है। संख्या ज्ञात करें।",
"A":"82",
"B":"88",
"C":"92",
"D":"96",
"Correct":"C"
},
{
"Question":"A shopkeeper gives a 25% discount on an article marked ₹2400. What is the selling price? / ₹2400 अंकित मूल्य वाली वस्तु पर 25% की छूट दी जाती है। विक्रय मूल्य कितना होगा?",
"A":"₹1700",
"B":"₹1750",
"C":"₹1800",
"D":"₹1850",
"Correct":"C"
},
{
"Question":"What is 35% of 800? / 800 का 35% कितना है?",
"A":"260",
"B":"270",
"C":"280",
"D":"290",
"Correct":"C"
},
{
"Question":"The area of a triangle having base 20 cm and height 12 cm is: / 20 सेमी आधार तथा 12 सेमी ऊँचाई वाले त्रिभुज का क्षेत्रफल कितना होगा?",
"A":"100 cm²",
"B":"110 cm²",
"C":"120 cm²",
"D":"130 cm²",
"Correct":"C"
}
]
